README.md
setup.py
cliptray/__init__.py
cliptray/__main__.py
cliptray/cliptray.py
cliptray/icon.py
cliptray.egg-info/PKG-INFO
cliptray.egg-info/SOURCES.txt
cliptray.egg-info/dependency_links.txt
cliptray.egg-info/entry_points.txt
cliptray.egg-info/requires.txt
cliptray.egg-info/top_level.txt