Metadata-Version: 2.1
Name: cliptray
Version: 1.0.0
Summary: A Tray icon tool allowing to quickly copy some values to the clipboard.
Home-page: https://github.com/McCzarny/cliptray
Author: Maciej Czarnecki
Author-email: mcczarny@gmail.com
License: The Unlicense
Platform: UNKNOWN
Classifier: License :: OSI Approved :: The Unlicense (Unlicense)
Classifier: Programming Language :: Python :: 3
Classifier: Programming Language :: Python :: 3.7
